[
  { "from": 1, "to": 38, "weight": 120 },
  { "from": 2, "to": 3, "weight": 106 },
  { "from": 3, "to": 4, "weight": 134 },
  { "from": 4, "to": 5, "weight": 96 },
  { "from": 5, "to": 38, "weight": 47 },
  { "from": 38, "to": 6, "weight": 49 },
  { "from": 6, "to": 7, "weight": 96 },
  { "from": 7, "to": 8, "weight": 192 },
  { "from": 8, "to": 39, "weight": 123 },
  { "from": 2, "to": 44, "weight": 43 },
  { "from": 44, "to": 10, "weight": 120 },
  { "from": 13, "to": 14, "weight": 106 },
  { "from": 14, "to": 15, "weight": 134 },
  { "from": 15, "to": 16, "weight": 96 },
  { "from": 16, "to": 17, "weight": 96 },
  { "from": 17, "to": 18, "weight": 96 },
  { "from": 18, "to": 19, "weight": 192 },
  { "from": 19, "to": 42, "weight": 123 },
  { "from": 13, "to": 45, "weight": 48 },
  { "from": 45, "to": 11, "weight": 224 },
  { "from": 13, "to": 9, "weight": 66 },
  { "from": 20, "to": 21, "weight": 106 },
  { "from": 21, "to": 22, "weight": 134 },
  { "from": 22, "to": 23, "weight": 96 },
  { "from": 23, "to": 24, "weight": 96 },
  { "from": 24, "to": 25, "weight": 96 },
  { "from": 25, "to": 26, "weight": 192 },
  { "from": 26, "to": 40, "weight": 123 },
  { "from": 20, "to": 46, "weight": 48 },
  { "from": 46, "to": 12, "weight": 80 },
  { "from": 2, "to": 13, "weight": 436 },
  { "from": 13, "to": 20, "weight": 404 },
  { "from": 3, "to": 14, "weight": 436 },
  { "from": 14, "to": 21, "weight": 404 },
  { "from": 4, "to": 15, "weight": 436 },
  { "from": 15, "to": 22, "weight": 404 },
  { "from": 5, "to": 16, "weight": 436 },
  { "from": 16, "to": 23, "weight": 404 },
  { "from": 6, "to": 17, "weight": 436 },
  { "from": 17, "to": 24, "weight": 404 },
  { "from": 7, "to": 18, "weight": 436 },
  { "from": 18, "to": 25, "weight": 404 },
  { "from": 8, "to": 19, "weight": 436 },
  { "from": 19, "to": 26, "weight": 404 },
  { "from": 39, "to": 42, "weight": 436 },
  { "from": 42, "to": 40, "weight": 404 },
  { "from": 42, "to": 31, "weight": 94 },
  { "from": 39, "to": 32, "weight": 170 },
  { "from": 23, "to": 33, "weight": 80 },
  { "from": 26, "to": 34, "weight": 80 },
  { "from": 40, "to": 35, "weight": 80 },
  { "from": 41, "to": 36, "weight": 166 },
  { "from": 18, "to": 41, "weight": 107 },
  { "from": 19, "to": 41, "weight": 85 },
  { "from": 16, "to": 37, "weight": 1 }
]
